README.md
initrd.py
setup.cfg
setup.py
initrd.egg-info/PKG-INFO
initrd.egg-info/SOURCES.txt
initrd.egg-info/dependency_links.txt
initrd.egg-info/top_level.txt